PhpJiaochengCYuyanBianchengWang/README.md
PhpJiaochengCYuyanBianchengWang/__init__.py
PhpJiaochengCYuyanBianchengWang/__main__.py
PhpJiaochengCYuyanBianchengWang/file.epub
PhpJiaochengCYuyanBianchengWang/index.html
PhpJiaochengCYuyanBianchengWang/css/__init__.py
PhpJiaochengCYuyanBianchengWang/css/annotations.css
PhpJiaochengCYuyanBianchengWang/css/main.css
PhpJiaochengCYuyanBianchengWang/css/normalize.css
PhpJiaochengCYuyanBianchengWang/css/popup.css
PhpJiaochengCYuyanBianchengWang/font/__init__.py
PhpJiaochengCYuyanBianchengWang/font/fontello.eot
PhpJiaochengCYuyanBianchengWang/font/fontello.svg
PhpJiaochengCYuyanBianchengWang/font/fontello.ttf
PhpJiaochengCYuyanBianchengWang/font/fontello.woff
PhpJiaochengCYuyanBianchengWang/img/__init__.py
PhpJiaochengCYuyanBianchengWang/img/annotator-glyph-sprite.png
PhpJiaochengCYuyanBianchengWang/img/annotator-icon-sprite.png
PhpJiaochengCYuyanBianchengWang/img/apple-touch-icon.png
PhpJiaochengCYuyanBianchengWang/img/cancelfullscreen.png
PhpJiaochengCYuyanBianchengWang/img/close.png
PhpJiaochengCYuyanBianchengWang/img/fullscreen.png
PhpJiaochengCYuyanBianchengWang/img/loader.gif
PhpJiaochengCYuyanBianchengWang/img/menu-icon.png
PhpJiaochengCYuyanBianchengWang/img/save.png
PhpJiaochengCYuyanBianchengWang/img/saved.png
PhpJiaochengCYuyanBianchengWang/img/settings-s.png
PhpJiaochengCYuyanBianchengWang/img/settings.png
PhpJiaochengCYuyanBianchengWang/img/star.png
PhpJiaochengCYuyanBianchengWang/js/__init__.py
PhpJiaochengCYuyanBianchengWang/js/epub.js
PhpJiaochengCYuyanBianchengWang/js/epub.min.js
PhpJiaochengCYuyanBianchengWang/js/epub.min.map
PhpJiaochengCYuyanBianchengWang/js/hooks.min.js
PhpJiaochengCYuyanBianchengWang/js/hooks.min.map
PhpJiaochengCYuyanBianchengWang/js/reader.js
PhpJiaochengCYuyanBianchengWang/js/reader.js.map
PhpJiaochengCYuyanBianchengWang/js/reader.min.js
PhpJiaochengCYuyanBianchengWang/js/reader.min.map
PhpJiaochengCYuyanBianchengWang/js/hooks/__init__.py
php_jiaocheng_c_yuyan_biancheng_wang-2024.3.5.0.dist-info/METADATA
php_jiaocheng_c_yuyan_biancheng_wang-2024.3.5.0.dist-info/WHEEL
php_jiaocheng_c_yuyan_biancheng_wang-2024.3.5.0.dist-info/entry_points.txt
php_jiaocheng_c_yuyan_biancheng_wang-2024.3.5.0.dist-info/top_level.txt
php_jiaocheng_c_yuyan_biancheng_wang-2024.3.5.0.dist-info/RECORD
